cookiecutter_django_package_instance/__init__.py
cookiecutter_django_package_instance/admin.py
cookiecutter_django_package_instance/apps.py
cookiecutter_django_package_instance/forms.py
cookiecutter_django_package_instance/migrations/__init__.py
cookiecutter_django_package_instance/models.py
cookiecutter_django_package_instance/tests.py
cookiecutter_django_package_instance/urls.py
cookiecutter_django_package_instance/views.py
cookiecutter_django_package_instance-2024.5.1.dist-info/LICENSE
cookiecutter_django_package_instance-2024.5.1.dist-info/METADATA
cookiecutter_django_package_instance-2024.5.1.dist-info/WHEEL
cookiecutter_django_package_instance-2024.5.1.dist-info/RECORD
