Metadata-Version: 2.1
Name: cookiecutter-django-package-instance
Version: 2024.5.1
Summary: A Django package that ...
Home-page: https://github.com/jacklinke/cookiecutter-django-package-instance
License: MIT
Author: Jack Linke
Author-email: jacklinke@gmail.com
Requires-Python: >=3.9,<4.0
Classifier: Development Status :: 1 - Planning
Classifier: Environment :: Web Environment
Classifier: Framework :: Django
Classifier: Framework :: Django :: 4.2
Classifier: Framework :: Django :: 5.0
Classifier: License :: OSI Approved :: MIT License
Classifier: Programming Language :: Python :: 3
Classifier: Programming Language :: Python :: 3.9
Classifier: Programming Language :: Python :: 3.10
Classifier: Programming Language :: Python :: 3.11
Classifier: Programming Language :: Python :: 3.12
Requires-Dist: click (>=8.1.7)
Requires-Dist: django (>=4.2)
Project-URL: Changelog, https://github.com/jacklinke/cookiecutter-django-package-instance/releases
Project-URL: Documentation, https://cookiecutter-django-package-instance.readthedocs.io
Project-URL: Repository, https://github.com/jacklinke/cookiecutter-django-package-instance
